Verilog/CombinationalLogic/FullAdder/fa.v
`timescale 1ns/1ns

module fa(input a, b, c, output sum, carry);
    assign sum = a ^ b ^ c;
    assign carry = ((a ^ b) & c) | (a & b);
endmodule

module faTest;
    reg a, b, c;
    wire sum, carry;
    integer i;

    fa uut(.a(a), .b(b), .c(c), .sum(sum), .carry(carry));

    initial begin
        
        a <= 0;
        b <= 0;
        c <= 0;

        $monitor("a = %b    b = %b    c = %b    sum = %b    carry = %b\n", a, b, c, sum, carry);
        $dumpfile("fa.vcd");
        $dumpvars(0, faTest);

        for(i = 0; i < 8; i = i + 1) begin
            {a, b, c} = i;
            #10;
        end
    end
endmodule

Verilog/Combinational/FullAdder/fa.vcd
$date
	Thu Jul 15 17:39:13 2021
$end
$version
	Icarus Verilog
$end
$timescale
	1ns
$end
$scope module faTest $end
$var wire 1 ! sum $end
$var wire 1 " carry $end
$var reg 1 # a $end
$var reg 1 $ b $end
$var reg 1 % c $end
$var integer 32 & i [31:0] $end
$scope module uut $end
$var wire 1 # a $end
$var wire 1 $ b $end
$var wire 1 % c $end
$var wire 1 " carry $end
$var wire 1 ! sum $end
$upscope $end
$upscope $end
$enddefinitions $end
#0
$dumpvars
b0 &
0%
0$
0#
0"
0!
$end
#10
1!
1%
b1 &
#20
1!
1$
0%
b10 &
#30
1"
0!
1%
b11 &
#40
0"
1!
1#
0$
0%
b100 &
#50
1"
0!
1%
b101 &
#60
0!
1$
0%
b110 &
#70
1!
1%
b111 &
#80
b1000 &
